expfactory_deploy_local/__init__.py
expfactory_deploy_local/cli.py
expfactory_deploy_local/serve.py
expfactory_deploy_local/utils.py
expfactory_deploy_local/static/favicon.ico
expfactory_deploy_local/static/css/bootstrap.min.css
expfactory_deploy_local/static/css/default_style.css
expfactory_deploy_local/static/css/expfactory.css
expfactory_deploy_local/static/css/fresh-bootstrap-table.css
expfactory_deploy_local/static/css/jspsych.css
expfactory_deploy_local/static/css/surveys.css
expfactory_deploy_local/static/fonts/glyphicons-halflings-regular.eot
expfactory_deploy_local/static/fonts/glyphicons-halflings-regular.svg
expfactory_deploy_local/static/fonts/glyphicons-halflings-regular.ttf
expfactory_deploy_local/static/fonts/glyphicons-halflings-regular.woff
expfactory_deploy_local/static/images/expfactoryticket.png
expfactory_deploy_local/static/images/expfactoryticketgray.png
expfactory_deploy_local/static/images/logo.png
expfactory_deploy_local/static/images/stanford.png
expfactory_deploy_local/static/images/tinypeople.png
expfactory_deploy_local/static/js/bootstrap-table.js
expfactory_deploy_local/static/js/bootstrap.min.js
expfactory_deploy_local/static/js/efSurvey.js
expfactory_deploy_local/static/js/jquery-1.11.2.min.js
expfactory_deploy_local/static/js/jquery-3.6.0.min.js
expfactory_deploy_local/static/js/jquery.min.js
expfactory_deploy_local/static/js/load_experiments.js
expfactory_deploy_local/static/js/math.min.js
expfactory_deploy_local/static/js/preview.js
expfactory_deploy_local/static/js/tipsy.js
expfactory_deploy_local/static/js/jquery/jquery-2.1.1.min.js
expfactory_deploy_local/static/js/jquery/jquery.wizard.js
expfactory_deploy_local/static/js/jquery/form/jquery.form-3.50.js
expfactory_deploy_local/static/js/jquery/ui/jquery-ui-1.10.4.custom.min.js
expfactory_deploy_local/static/js/jquery/ui/smoothness/jquery-ui-1.10.4.custom.min.css
expfactory_deploy_local/static/js/jquery/ui/smoothness/images/animated-overlay.gif
expfactory_deploy_local-0.1.0.dev7.dist-info/METADATA
expfactory_deploy_local-0.1.0.dev7.dist-info/WHEEL
expfactory_deploy_local-0.1.0.dev7.dist-info/entry_points.txt
expfactory_deploy_local-0.1.0.dev7.dist-info/RECORD
