Metadata-Version: 2.1
Name: expfactory-deploy-local
Version: 0.1.0.dev7
Author-email: Ross Blair <rosswilsonblair@gmail.com>
License: MIT License
Requires-Python: >=3.8
Requires-Dist: jinja2>=3.1.2
Requires-Dist: web-py>=0.62
